MANIFEST.in
README.txt
setup.cfg
setup.py
QuickWiki.egg-info/PKG-INFO
QuickWiki.egg-info/SOURCES.txt
QuickWiki.egg-info/dependency_links.txt
QuickWiki.egg-info/entry_points.txt
QuickWiki.egg-info/not-zip-safe
QuickWiki.egg-info/paster_plugins.txt
QuickWiki.egg-info/requires.txt
QuickWiki.egg-info/top_level.txt
quickwiki/__init__.py
quickwiki/websetup.py
quickwiki/config/__init__.py
quickwiki/config/deployment.ini_tmpl
quickwiki/config/environment.py
quickwiki/config/middleware.py
quickwiki/config/routing.py
quickwiki/controllers/__init__.py
quickwiki/controllers/error.py
quickwiki/controllers/pages.py
quickwiki/lib/__init__.py
quickwiki/lib/app_globals.py
quickwiki/lib/base.py
quickwiki/lib/helpers.py
quickwiki/model/__init__.py
quickwiki/model/meta.py
quickwiki/public/favicon.ico
quickwiki/public/quick.css
quickwiki/templates/base.mako
quickwiki/templates/pages/edit.mako
quickwiki/templates/pages/index.mako
quickwiki/templates/pages/new.mako
quickwiki/templates/pages/show.mako
quickwiki/tests/__init__.py
quickwiki/tests/test_models.py
quickwiki/tests/functional/__init__.py
quickwiki/tests/functional/test_pages.py