Metadata-Version: 1.0
Name: QuickWiki
Version: 0.1.6
Summary: QuickWiki - Pylons 0.9.7 Tutorial application
Home-page: http://pylonshq.com/docs/en/0.9.7/tutorials/quickwiki_tutorial/
Author: UNKNOWN
Author-email: UNKNOWN
License: UNKNOWN
Platform: UNKNOWN
